fast_s3_url/__init__.py
fast_s3_url/credentials.py
fast_s3_url/py.typed
fast_s3_url/s3_signer.py
fast_s3_url/util.py
fast_s3_url-0.2.0.dist-info/LICENSE
fast_s3_url-0.2.0.dist-info/WHEEL
fast_s3_url-0.2.0.dist-info/METADATA
fast_s3_url-0.2.0.dist-info/RECORD
