Metadata-Version: 2.1
Name: fast-s3-url
Version: 0.2.0
Summary: An S3 signed URL generator, faster than boto3 and aiobotocore's, for generating lots of signed URLs quickly.
Home-page: https://github.com/RedRoserade/py-fast-s3-url
License: MIT
Author: André Carvalho
Author-email: afecarvalho@gmail.com
Requires-Python: >=3.8,<4.0
Classifier: License :: OSI Approved :: MIT License
Classifier: Programming Language :: Python :: 3
Classifier: Programming Language :: Python :: 3.8
Classifier: Programming Language :: Python :: 3.9
Classifier: Programming Language :: Python :: 3.10
Classifier: Programming Language :: Python :: 3.11
Project-URL: Repository, https://github.com/RedRoserade/py-fast-s3-url
